{
    "generatedAt":  "2026-02-27 22:11:44",
    "status":  "PASS",
    "source":  "20_phase9_app_batch_plan_latest.json",
    "cardCount":  6,
    "cards":  [
                  {
                      "id":  "APP-ISSUE-01",
                      "title":  "[Phase9][APP-SPRINT-1] BATCH-1 parser/mapping closure",
                      "sprint":  "APP-SPRINT-1",
                      "priority":  "P0",
                      "sourceBatch":  "BATCH-1",
                      "size":  4,
                      "checklist":  [
                                        "`createCompany` response parser (`companyId`, `ownerMember`, `createdAt`)",
                                        "`createCompanyRoute` parser (`routeId`, `srvCode`)",
                                        "`createVehicle` parser",
                                        "`listCompanyMembers` parser (`uid`, `role`, `memberStatus`, `displayName/email/phone`)"
                                    ],
                      "doneCriteria":  [
                                           "ilgili parser veya mapping kodu app tarafinda uygulanmis",
                                           "07 checklist\u0027te bu itemlar [x] olmus",
                                           "ilgili smoke senaryosu PASS ve kanit eklenmis"
                                       ],
                      "reportTemplate":  [
                                             "Degisen dosyalar",
                                             "Kosulan testler",
                                             "Kalan aciklar",
                                             "Risk notu"
                                         ]
                  },
                  {
                      "id":  "APP-ISSUE-02",
                      "title":  "[Phase9][APP-SPRINT-1] BATCH-2 parser/mapping closure",
                      "sprint":  "APP-SPRINT-1",
                      "priority":  "P0",
                      "sourceBatch":  "BATCH-2",
                      "size":  4,
                      "checklist":  [
                                        "`listCompanyVehicles` parser",
                                        "`listMyCompanies` parser (`companyId`, `name`, `role`, `memberStatus`)",
                                        "`updateCompanyRoute` parser + `lastKnownUpdateToken` parity",
                                        "`updateVehicle` parser"
                                    ],
                      "doneCriteria":  [
                                           "ilgili parser veya mapping kodu app tarafinda uygulanmis",
                                           "07 checklist\u0027te bu itemlar [x] olmus",
                                           "ilgili smoke senaryosu PASS ve kanit eklenmis"
                                       ],
                      "reportTemplate":  [
                                             "Degisen dosyalar",
                                             "Kosulan testler",
                                             "Kalan aciklar",
                                             "Risk notu"
                                         ]
                  },
                  {
                      "id":  "APP-ISSUE-03",
                      "title":  "[Phase9][APP-SPRINT-1] BATCH-3 parser/mapping closure",
                      "sprint":  "APP-SPRINT-1",
                      "priority":  "P0",
                      "sourceBatch":  "BATCH-3",
                      "size":  4,
                      "checklist":  [
                                        "Active company resolver (login -\u003e mode -\u003e company fallback)",
                                        "`426 Upgrade Required`",
                                        "`ACTIVE_TRIP_ROUTE_STRUCTURE_LOCKED`",
                                        "`deleteCompanyRouteStop` parser"
                                    ],
                      "doneCriteria":  [
                                           "ilgili parser veya mapping kodu app tarafinda uygulanmis",
                                           "07 checklist\u0027te bu itemlar [x] olmus",
                                           "ilgili smoke senaryosu PASS ve kanit eklenmis"
                                       ],
                      "reportTemplate":  [
                                             "Degisen dosyalar",
                                             "Kosulan testler",
                                             "Kalan aciklar",
                                             "Risk notu"
                                         ]
                  },
                  {
                      "id":  "APP-ISSUE-04",
                      "title":  "[Phase9][APP-SPRINT-2] BATCH-4 parser/mapping closure",
                      "sprint":  "APP-SPRINT-2",
                      "priority":  "P0",
                      "sourceBatch":  "BATCH-4",
                      "size":  4,
                      "checklist":  [
                                        "`listActiveTripsByCompany` parser",
                                        "`listCompanyRouteStops` parser",
                                        "`live.source` (`rtdb|trip_doc`) fallback mapping",
                                        "`liveState` (`online|stale`) UI mapping"
                                    ],
                      "doneCriteria":  [
                                           "ilgili parser veya mapping kodu app tarafinda uygulanmis",
                                           "07 checklist\u0027te bu itemlar [x] olmus",
                                           "ilgili smoke senaryosu PASS ve kanit eklenmis"
                                       ],
                      "reportTemplate":  [
                                             "Degisen dosyalar",
                                             "Kosulan testler",
                                             "Kalan aciklar",
                                             "Risk notu"
                                         ]
                  },
                  {
                      "id":  "APP-ISSUE-05",
                      "title":  "[Phase9][APP-SPRINT-2] BATCH-5 parser/mapping closure",
                      "sprint":  "APP-SPRINT-2",
                      "priority":  "P0",
                      "sourceBatch":  "BATCH-5",
                      "size":  4,
                      "checklist":  [
                                        "`reorderCompanyRouteStops` parser (`changed`, `updatedAt`)",
                                        "`ROUTE_STOP_INVALID_STATE`",
                                        "`ROUTE_STOP_REORDER_STATE_INVALID`",
                                        "`UPDATE_TOKEN_MISMATCH`"
                                    ],
                      "doneCriteria":  [
                                           "ilgili parser veya mapping kodu app tarafinda uygulanmis",
                                           "07 checklist\u0027te bu itemlar [x] olmus",
                                           "ilgili smoke senaryosu PASS ve kanit eklenmis"
                                       ],
                      "reportTemplate":  [
                                             "Degisen dosyalar",
                                             "Kosulan testler",
                                             "Kalan aciklar",
                                             "Risk notu"
                                         ]
                  },
                  {
                      "id":  "APP-ISSUE-06",
                      "title":  "[Phase9][APP-SPRINT-2] BATCH-6 parser/mapping closure",
                      "sprint":  "APP-SPRINT-2",
                      "priority":  "P0",
                      "sourceBatch":  "BATCH-6",
                      "size":  4,
                      "checklist":  [
                                        "`upsertCompanyRouteStop` parser",
                                        "RTDB stream state mapping (`live`, `mismatch`, `error`, `access_denied`)",
                                        "Company context recoverability (logout/login + mode switch)",
                                        "Error message mapping smoke (all listed codes)"
                                    ],
                      "doneCriteria":  [
                                           "ilgili parser veya mapping kodu app tarafinda uygulanmis",
                                           "07 checklist\u0027te bu itemlar [x] olmus",
                                           "ilgili smoke senaryosu PASS ve kanit eklenmis"
                                       ],
                      "reportTemplate":  [
                                             "Degisen dosyalar",
                                             "Kosulan testler",
                                             "Kalan aciklar",
                                             "Risk notu"
                                         ]
                  }
              ]
}
